viola/__init__.py
viola/_exceptions.py
viola/_typing.py
viola/_version.py
viola/testing.py
viola/cli/__init__.py
viola/cli/matrix_generator.py
viola/cli/signature_extractor.py
viola/cli/vcf2bedpe.py
viola/cli/viola.py
viola/core/__init__.py
viola/core/api.py
viola/core/bed.py
viola/core/bedpe.py
viola/core/cohort.py
viola/core/concat.py
viola/core/fasta.py
viola/core/indexing.py
viola/core/merge.py
viola/core/vcf.py
viola/data/sv_class_article.txt
viola/data/sv_class_default.txt
viola/io/__init__.py
viola/io/_vcf_parser.py
viola/io/api.py
viola/io/fasta_io.py
viola/io/multi_parser.py
viola/io/parser.py
viola/ml/__init__.py
viola/ml/_constrained_kmeans.py
viola/ml/api.py
viola/ml/extractor.py
viola/utils/__init__.py
viola/utils/api.py
viola/utils/cluster.py
viola/utils/microhomology.py
viola/utils/utils.py
Viola_SV-1.0.2.dist-info/LICENSE
Viola_SV-1.0.2.dist-info/METADATA
Viola_SV-1.0.2.dist-info/WHEEL
Viola_SV-1.0.2.dist-info/entry_points.txt
Viola_SV-1.0.2.dist-info/top_level.txt
Viola_SV-1.0.2.dist-info/RECORD
