Metadata-Version: 2.1
Name: Viola-SV
Version: 1.0.2
Summary: SV signature analysis tool with custom SV type
Home-page: https://github.com/dermasugita/Viola-SV
Author: Itsuki Sugita, Shohei Matsuyama, Hiroki Dobashi
Author-email: itsukiisogin@gmail.com
License: Apache License 2.0
Keywords: bioinformatics
Platform: UNKNOWN
Classifier: Programming Language :: Python :: 3
Classifier: Programming Language :: Python :: 3 :: Only
Classifier: Programming Language :: Python :: 3.6
Classifier: Programming Language :: Python :: 3.7
Classifier: Programming Language :: Python :: 3.8
Classifier: Programming Language :: Python :: 3.9
Classifier: Intended Audience :: Science/Research
Classifier: License :: OSI Approved :: Apache Software License
Classifier: Operating System :: OS Independent
Requires-Python: >=3.6
License-File: LICENSE
Requires-Dist: pandas (>=1.1.5)
Requires-Dist: PyVCF (>=0.6.8)
Requires-Dist: intervaltree (>=3.1.0)
Requires-Dist: biopython (>=1.79)
Requires-Dist: scikit-learn (>=0.24.2)
Requires-Dist: scipy (>=1.5.4)
Requires-Dist: click (>=8.0.4)
Provides-Extra: test
Requires-Dist: pytest ; extra == 'test'
